infisical/__init__.py
infisical/_types.py
infisical/exceptions.py
infisical/utils.py
infisical/clients/__init__.py
infisical/clients/base.py
infisical/clients/clients.py
infisical/credentials/__init__.py
infisical/credentials/keyring_handler.py
infisical/credentials/providers.py
infisical/resources/__init__.py
infisical/resources/base.py
infisical/resources/certificates/__init__.py
infisical/resources/certificates/api.py
infisical/resources/certificates/models.py
infisical/resources/folders/__init__.py
infisical/resources/folders/api.py
infisical/resources/folders/models.py
infisical/resources/secrets/__init__.py
infisical/resources/secrets/api.py
infisical/resources/secrets/models.py
infisical_httpx_sdk-1.1.0.dist-info/licenses/LICENSE
infisical_httpx_sdk-1.1.0.dist-info/METADATA
infisical_httpx_sdk-1.1.0.dist-info/WHEEL
infisical_httpx_sdk-1.1.0.dist-info/top_level.txt
infisical_httpx_sdk-1.1.0.dist-info/RECORD
