Metadata-Version: 2.4
Name: infisical-httpx-sdk
Version: 1.1.0
Summary: The Un-official Infisical Python SDK using HTTPX 
Author: riebecj
License:                                  Apache License
Project-URL: Repository, https://github.com/riebecj/infisical-httpx-sdk
Project-URL: Issues, https://github.com/riebecj/infisical-httpx-sdk/issues
Project-URL: Documentation, https://riebecj.github.io/infisical-httpx-sdk/
Keywords: infisical-python-sdk,infisical-httpx-sdk,infisical-sdk,infisical,secrets,secrets-management,pki,kms,httpx
Classifier: Operating System :: OS Independent
Classifier: Programming Language :: Python :: 3.11
Classifier: Programming Language :: Python :: 3.12
Classifier: Development Status :: 3 - Alpha
Classifier: Environment :: Web Environment
Classifier: Framework :: Pydantic :: 2
Classifier: Framework :: AsyncIO
Classifier: Intended Audience :: Developers
Classifier: Intended Audience :: End Users/Desktop
Classifier: Intended Audience :: Information Technology
Classifier: Intended Audience :: System Administrators
Classifier: License :: OSI Approved :: Apache Software License
Classifier: Programming Language :: Python :: 3 :: Only
Classifier: Programming Language :: Python :: 3.11
Classifier: Topic :: Security
Classifier: Topic :: Software Development
Classifier: Topic :: Software Development :: Libraries :: Python Modules
Classifier: Topic :: Utilities
Requires-Python: >=3.11
License-File: LICENSE
Requires-Dist: httpx==0.28.1
Requires-Dist: jwcrypto==1.5.6
Requires-Dist: keyring==25.6.0
Requires-Dist: pydantic==2.11.4
Provides-Extra: dev
Requires-Dist: handsdown~=2.1; extra == "dev"
Requires-Dist: mkdocs~=1.6; extra == "dev"
Requires-Dist: mkdocs-gen-files~=0.5; extra == "dev"
Requires-Dist: mkdocs-material~=9.6; extra == "dev"
Requires-Dist: mkdocstrings[python]~=0.18; extra == "dev"
Requires-Dist: mkdocstrings-python-xref~=1.16; extra == "dev"
Requires-Dist: pytest~=8.3; extra == "dev"
Requires-Dist: pytest-asyncio~=0.26; extra == "dev"
Requires-Dist: pytest-cov~=6.1; extra == "dev"
Requires-Dist: ruff~=0.11; extra == "dev"
Dynamic: license-file
